{
  "data": {
    "_serverScript": [
      {
        "path": "server/server_script"
      }
    ],
    "actorName": {
      "asset": "asset/Mesh/Item/zone3/coinLV5_Z3/actor.actor",
      "selector": "editor/SourcesMain/asset/Mesh/Item/zone3/coinLV5_Z3/actor.actor"
    },
    "AI_attack": {
      "enable": true
    },
    "AI_patrol": {
      "patrolMode": "randomPath"
    },
    "autoMove": true,
    "boundingVolume": {
      "height": 2,
      "radius": 1,
      "type": "Capsule"
    },
    "canJump": false,
    "canMove": false,
    "canRevive": true,
    "collision": true,
    "deadAction": {
      "deathHideTime": {
        "value": 60
      },
      "playDeadAction": "die_front"
    },
    "deadSound": {
      "volume": {
        "value": 0
      }
    },
    "equip": [
      "1",
      "2"
    ],
    "hideHp": false,
    "maxHp": 64,
    "name": {
      "value": "dfdf03e1-9786-4e04-ad6e-93b1bbf4f9a9"
    },
    "reviveTime": {
      "value": 40
    }
  },
  "meta": {
    "EXPORT": {
      "setting.json": "2bc6b288b52cbb88d8a5eba47adac7e3",
      "triggers.bts": ""
    },
    "VERSION": "0.20"
  }
}